sshsig/__init__.py
sshsig/_version.py
sshsig/allowed_signers.py
sshsig/binary_io.py
sshsig/py.typed
sshsig/ssh_public_key.py
sshsig/sshsig.py
sshsig/unexceptional.py
sshsig-0.3.1.dist-info/LICENSE
sshsig-0.3.1.dist-info/METADATA
sshsig-0.3.1.dist-info/WHEEL
sshsig-0.3.1.dist-info/top_level.txt
sshsig-0.3.1.dist-info/RECORD
