Metadata-Version: 2.1
Name: sshsig
Version: 0.3.1
Summary: SSH signature verification
Maintainer-email: Castedo Ellerman <castedo@castedo.com>, Jelmer Vernooij <jelmer@jelmer.uk>
License: MIT License
Project-URL: GitHub, https://github.com/castedo/sshsig
Project-URL: GitLab, https://gitlab.com/perm.pub/sshsiglib
Classifier: Programming Language :: Python :: 3
Classifier: License :: OSI Approved :: MIT License
Classifier: Operating System :: POSIX
Requires-Python: >=3.9
License-File: LICENSE
Requires-Dist: cryptography
